batchwizard/__init__.py
batchwizard/cli.py
batchwizard/config.py
batchwizard/models.py
batchwizard/processor.py
batchwizard/ui.py
batchwizard/utils.py
batchwizard-0.2.0.dist-info/LICENSE
batchwizard-0.2.0.dist-info/METADATA
batchwizard-0.2.0.dist-info/WHEEL
batchwizard-0.2.0.dist-info/entry_points.txt
batchwizard-0.2.0.dist-info/RECORD
