Metadata-Version: 2.1
Name: batchwizard
Version: 0.2.0
Summary: BatchWizard: Manage OpenAI batch processing jobs with ease
Home-page: https://github.com/cmakafui/batchwizard
License: MIT
Keywords: openai,batch,cli,async
Author: Carl Kugblenu
Requires-Python: >=3.9,<4.0
Classifier: License :: OSI Approved :: MIT License
Classifier: Programming Language :: Python :: 3
Classifier: Programming Language :: Python :: 3.9
Classifier: Programming Language :: Python :: 3.10
Classifier: Programming Language :: Python :: 3.11
Classifier: Programming Language :: Python :: 3.12
Requires-Dist: aiofiles (>=24.1.0,<25.0.0)
Requires-Dist: loguru (>=0.7.2,<0.8.0)
Requires-Dist: openai (>=1.37.0,<2.0.0)
Requires-Dist: pydantic (>=2.8.2,<3.0.0)
Requires-Dist: pydantic-settings (>=2.3.4,<3.0.0)
Requires-Dist: python-dotenv (>=1.0.1,<2.0.0)
Requires-Dist: rich (>=13.7.1,<14.0.0)
Requires-Dist: typer (>=0.12.3,<0.13.0)
Project-URL: Repository, https://github.com/cmakafui/batchwizard
